README.md
setup.py
sysprl/__init__.py
sysprl/sysprl.py
sysprl.egg-info/PKG-INFO
sysprl.egg-info/SOURCES.txt
sysprl.egg-info/dependency_links.txt
sysprl.egg-info/requires.txt
sysprl.egg-info/top_level.txt